l1st/__init__.py
l1st-127.0.1.dist-info/LICENSE
l1st-127.0.1.dist-info/METADATA
l1st-127.0.1.dist-info/WHEEL
l1st-127.0.1.dist-info/top_level.txt
l1st-127.0.1.dist-info/RECORD
